{
	"cmake" : 
	{
		"generator" : 
		{
			"name" : "Ninja"
		},
		"paths" : 
		{
			"cmake" : "D:/Program Files/MSVS/Common7/IDE/CommonExtensions/Microsoft/CMake/CMake/bin/cmake.exe",
			"cpack" : "D:/Program Files/MSVS/Common7/IDE/CommonExtensions/Microsoft/CMake/CMake/bin/cpack.exe",
			"ctest" : "D:/Program Files/MSVS/Common7/IDE/CommonExtensions/Microsoft/CMake/CMake/bin/ctest.exe",
			"root" : "D:/Program Files/MSVS/Common7/IDE/CommonExtensions/Microsoft/CMake/CMake/share/cmake-3.14"
		},
		"version" : 
		{
			"isDirty" : false,
			"major" : 3,
			"minor" : 14,
			"patch" : 19050301,
			"string" : "3.14.19050301-MSVC_2",
			"suffix" : ""
		}
	},
	"objects" : 
	[
		{
			"jsonFile" : "codemodel-v2-1e6963c4d243ca80adc1.json",
			"kind" : "codemodel",
			"version" : 
			{
				"major" : 2,
				"minor" : 0
			}
		},
		{
			"jsonFile" : "cache-v2-53af63cf3e6f12170d0a.json",
			"kind" : "cache",
			"version" : 
			{
				"major" : 2,
				"minor" : 0
			}
		},
		{
			"jsonFile" : "cmakeFiles-v1-a77ec34e6ba04b623abc.json",
			"kind" : "cmakeFiles",
			"version" : 
			{
				"major" : 1,
				"minor" : 0
			}
		}
	],
	"reply" : 
	{
		"client-MicrosoftVS" : 
		{
			"query.json" : 
			{
				"requests" : 
				[
					{
						"kind" : "cache",
						"version" : 2
					},
					{
						"kind" : "cmakeFiles",
						"version" : 1
					},
					{
						"kind" : "codemodel",
						"version" : 2
					}
				],
				"responses" : 
				[
					{
						"jsonFile" : "cache-v2-53af63cf3e6f12170d0a.json",
						"kind" : "cache",
						"version" : 
						{
							"major" : 2,
							"minor" : 0
						}
					},
					{
						"jsonFile" : "cmakeFiles-v1-a77ec34e6ba04b623abc.json",
						"kind" : "cmakeFiles",
						"version" : 
						{
							"major" : 1,
							"minor" : 0
						}
					},
					{
						"jsonFile" : "codemodel-v2-1e6963c4d243ca80adc1.json",
						"kind" : "codemodel",
						"version" : 
						{
							"major" : 2,
							"minor" : 0
						}
					}
				]
			}
		}
	}
}
